ncsw_data/__init__.py
ncsw_data/source/__init__.py
ncsw_data/source/base/__init__.py
ncsw_data/source/base/base.py
ncsw_data/source/base/utility/__init__.py
ncsw_data/source/base/utility/download.py
ncsw_data/source/compound/__init__.py
ncsw_data/source/compound/compound.py
ncsw_data/source/compound/chembl/__init__.py
ncsw_data/source/compound/chembl/chembl.py
ncsw_data/source/compound/chembl/utility/__init__.py
ncsw_data/source/compound/chembl/utility/download.py
ncsw_data/source/compound/chembl/utility/extraction.py
ncsw_data/source/compound/chembl/utility/formatting.py
ncsw_data/source/compound/coconut/__init__.py
ncsw_data/source/compound/coconut/coconut.py
ncsw_data/source/compound/coconut/utility/__init__.py
ncsw_data/source/compound/coconut/utility/download.py
ncsw_data/source/compound/coconut/utility/extraction.py
ncsw_data/source/compound/coconut/utility/formatting.py
ncsw_data/source/compound/miscellaneous/__init__.py
ncsw_data/source/compound/miscellaneous/miscellaneous.py
ncsw_data/source/compound/miscellaneous/utility/__init__.py
ncsw_data/source/compound/miscellaneous/utility/download.py
ncsw_data/source/compound/miscellaneous/utility/extraction.py
ncsw_data/source/compound/miscellaneous/utility/formatting.py
ncsw_data/source/compound/zinc/__init__.py
ncsw_data/source/compound/zinc/zinc.py
ncsw_data/source/compound/zinc/utility/__init__.py
ncsw_data/source/compound/zinc/utility/download.py
ncsw_data/source/compound/zinc/utility/extraction.py
ncsw_data/source/compound/zinc/utility/formatting.py
ncsw_data/source/compound_pattern/__init__.py
ncsw_data/source/compound_pattern/compound_pattern.py
ncsw_data/source/compound_pattern/rdkit/__init__.py
ncsw_data/source/compound_pattern/rdkit/rdkit.py
ncsw_data/source/compound_pattern/rdkit/utility/__init__.py
ncsw_data/source/compound_pattern/rdkit/utility/download.py
ncsw_data/source/compound_pattern/rdkit/utility/extraction.py
ncsw_data/source/compound_pattern/rdkit/utility/formatting.py
ncsw_data-2025.9.1.dist-info/licenses/LICENSE
ncsw_data-2025.9.1.dist-info/METADATA
ncsw_data-2025.9.1.dist-info/WHEEL
ncsw_data-2025.9.1.dist-info/top_level.txt
ncsw_data-2025.9.1.dist-info/RECORD
