Metadata-Version: 2.4
Name: ncsw-data
Version: 2025.9.1
Summary: The NeoChemSynthWave: Data project.
Author: Haris Hasic
Keywords: chemical-compound-patterns,,chemical-compounds,,chemical-reaction-patterns,,chemical-reactions,,chemical-synthesis,,data,,data-source,,database,,dataset,,retrosynthesis,,retrosynthetic-analysis,,synthesizability,,synthetic-accessibility,,synthetic-complexity
License-File: LICENSE
Requires-Dist: ord-schema
Requires-Dist: py7zr
Requires-Dist: pyarrow
Requires-Dist: pqdm
Requires-Dist: rdkit
Requires-Dist: requests
Requires-Dist: tqdm
Dynamic: license-file
